cfn_tools-0.1.6.dist-info/METADATA
cfn_tools-0.1.6.dist-info/RECORD
cfn_tools-0.1.6.dist-info/WHEEL
cfn_tools-0.1.6.dist-info/entry_points.txt
cfn_tools-0.1.6.dist-info/top_level.txt
cfntools/__init__.py
cfntools/cli.py
cfntools/diff.py
cfntools/ls.py
cfntools/validate.py
