Metadata-Version: 2.1
Name: cfn-tools
Version: 0.1.6
Summary: Tools for AWS CloudFormation
Home-page: https://github.com/boroivanov/cfn-tools
Author: Borislav Ivanov
Author-email: borogl@gmail.com
License: MIT license
Platform: UNKNOWN
Classifier: Development Status :: 2 - Pre-Alpha
Classifier: Programming Language :: Python
Classifier: Programming Language :: Python :: 2
Classifier: Programming Language :: Python :: 2.7
Requires-Dist: Click (>=6.0)
Requires-Dist: boto3 (>=1.3.1)
